crossai/__init__.py
crossai/_generate_transformers.py
crossai/models/__init__.py
crossai/models/nn1d/__init__.py
crossai/models/nn1d/_bilstm.py
crossai/models/nn1d/_cnn_3layer.py
crossai/models/nn1d/_inceptiontime.py
crossai/models/nn1d/_layers.py
crossai/models/nn1d/_xceptiontime.py
crossai/models/nn2d/__init__.py
crossai/models/nn2d/_inception.py
crossai/models/nn2d/_layers.py
crossai/models/nn2d/_resnet.py
crossai/models/nn2d/_resnet34.py
crossai/models/nn2d/_resnet50.py
crossai/models/nn2d/_utils.py
crossai/models/nn2d/_vgg16.py
crossai/models/nn2d/_xception.py
crossai/models/nn2d/_xception_func.py
crossai/perfomance/__init__.py
crossai/perfomance/evaluation/__init__.py
crossai/perfomance/evaluation/_confidence_booster.py
crossai/perfomance/evaluation/_detection_metrics.py
crossai/perfomance/evaluation/_model_evaluation.py
crossai/perfomance/evaluation/_trust_scores_utils.py
crossai/preparation/__init__.py
crossai/preparation/augmentation/__init__.py
crossai/preparation/augmentation/_augmentation.py
crossai/preparation/augmentation/_custom_augmentations.py
crossai/preparation/augmentation/_specaugment.py
crossai/preparation/encoding/__init__.py
crossai/preparation/encoding/_encoder.py
crossai/preparation/encoding/_utils.py
crossai/preparation/scaler/__init__.py
crossai/preparation/scaler/_scaler.py
crossai/preparation/scaler/_utils.py
crossai/preparation/transformation/__init__.py
crossai/preparation/transformation/_transformation.py
crossai/preparation/transformation/_utils.py
crossai/processing/__init__.py
crossai/processing/_utils.py
crossai/processing/audio/__init__.py
crossai/processing/audio/_audio.py
crossai/processing/audio/_custom_features.py
crossai/processing/audio/_custom_processing.py
crossai/processing/motion/__init__.py
crossai/processing/motion/_motion.py
crossai/processing/signal/__init__.py
crossai/processing/signal/_custom_features.py
crossai/processing/signal/_custom_processing.py
crossai/processing/signal/_signal.py
crossai-0.0.0.15.dist-info/LICENSE
crossai-0.0.0.15.dist-info/METADATA
crossai-0.0.0.15.dist-info/WHEEL
crossai-0.0.0.15.dist-info/top_level.txt
crossai-0.0.0.15.dist-info/RECORD
