Metadata-Version: 2.1
Name: crossai
Version: 0.0.0.15
Summary: A library of high-level functionalities capable of handling end-to-end Artificial Intelligence pipelines for Time-Series analysis
Home-page: https://github.com/tzamalisp/crossai-lib
Author: Pantelis Tzamalis, Constantinos Tsakonas, Dimitrios Markantonatos, Andreas Bardoutsos
Author-email: tzamalispantelis@gmail.com
License: GNU General Public License v3.0
Requires-Python: >=3.8
License-File: LICENSE
Requires-Dist: librosa (==0.9.2)
Requires-Dist: alibi
Requires-Dist: numpy (>=1.22.0)
Requires-Dist: pandas (>=1.4.0)
Requires-Dist: resampy (>=0.4.0)
Requires-Dist: scikit-learn (>=1.1.3)
Requires-Dist: scipy (>=1.8.0)
Requires-Dist: setuptools (>=61.2.0)
Requires-Dist: tensorflow-addons (>=0.17.1)
Requires-Dist: toml (>=0.10.2)
Requires-Dist: tqdm (>=4.64.1)
Requires-Dist: albumentations (>=1.3.0)
Requires-Dist: audiomentations (>=0.28.0)
Requires-Dist: tsaug (>=0.1.0)
Requires-Dist: seaborn (>=0.11.2)
Requires-Dist: matplotlib (>=3.4.3)
Requires-Dist: nlpaug (==1.1.11)
Requires-Dist: tensorflow-macos (==2.11.0) ; platform_system == "Darwin"
Requires-Dist: tensorflow-metal (==0.7.0) ; platform_system == "Darwin"
Requires-Dist: tensorflow (==2.11.0) ; platform_system == "Linux"
